django_8e9e15_v1-0.1.55.dist-info/licenses/LICENSE
libsv1/__init__.py
libsv1/apps/api_doc/README.md
libsv1/apps/api_doc/__init__.py
libsv1/apps/api_doc/apps.py
libsv1/apps/api_doc/urls.py
libsv1/apps/api_doc/views.py
libsv1/apps/api_doc/templates/drf_spectacular/swagger_ui.html
libsv1/apps/global_system_log/README.md
libsv1/apps/global_system_log/__init__.py
libsv1/apps/global_system_log/apps.py
libsv1/apps/global_system_log/middleware.py
libsv1/apps/global_system_log/models.py
libsv1/apps/global_system_log/services.py
libsv1/apps/global_system_log/tasks.py
libsv1/apps/global_system_log/migrations/0001_initial.py
libsv1/apps/global_system_log/migrations/__init__.py
libsv1/exceptions/base_api/README.md
libsv1/exceptions/base_api/__init__.py
libsv1/exceptions/base_api/exceptions.py
libsv1/exceptions/base_api/middleware.py
libsv1/middlewares/query_profiler.py
libsv1/middlewares/remove_slash.py
libsv1/middlewares/request_normalizer.py
libsv1/middlewares/update_request.py
libsv1/middlewares/db_reconnect/README.md
libsv1/middlewares/db_reconnect/__init__.py
libsv1/middlewares/db_reconnect/core.py
libsv1/middlewares/db_reconnect/decorators.py
libsv1/middlewares/db_reconnect/middleware.py
libsv1/mixins/api_view.py
libsv1/mixins/dataset.py
libsv1/mixins/model.py
libsv1/mixins/test_case.py
libsv1/modules/asoq/README.md
libsv1/modules/asoq/__init__.py
libsv1/modules/asoq/asoq.py
libsv1/patches/dprint.py
libsv1/permissions/base.py
libsv1/serializers/base_api.py
libsv1/services/ai.py
libsv1/services/branchio.py
libsv1/services/chottu.py
libsv1/services/firebase.py
libsv1/services/geocode.py
libsv1/services/mailgun.py
libsv1/services/onesignal.py
libsv1/services/pusher.py
libsv1/services/twilio.py
libsv1/utils/base.py
libsv1/utils/carbon.py
libsv1/utils/collection.py
libsv1/utils/console.py
libsv1/utils/fake.py
libsv1/utils/file.py
libsv1/utils/math.py
libsv1/utils/model.py
libsv1/utils/oauth.py
libsv1/utils/request.py
libsv1/utils/string.py
libsv1/validators/api_request.py
django_8e9e15_v1-0.1.55.dist-info/METADATA
django_8e9e15_v1-0.1.55.dist-info/WHEEL
django_8e9e15_v1-0.1.55.dist-info/top_level.txt
django_8e9e15_v1-0.1.55.dist-info/RECORD
