Metadata-Version: 2.4
Name: django-8e9e15-v1
Version: 0.1.55
Summary: A comprehensive static utility class for various string manipulations in Python.
Author-email: Nick <nickgotras@gmail.com>
License-Expression: LGPL-3.0-or-later
Classifier: Programming Language :: Python :: 3
Requires-Python: >=3.11
License-File: LICENSE
Dynamic: license-file
